llama_index/llms/mistral_rs/__init__.py
llama_index/llms/mistral_rs/base.py
llama_index_llms_mistral_rs-0.4.1.dist-info/METADATA
llama_index_llms_mistral_rs-0.4.1.dist-info/WHEEL
llama_index_llms_mistral_rs-0.4.1.dist-info/licenses/LICENSE
llama_index_llms_mistral_rs-0.4.1.dist-info/RECORD
