Metadata-Version: 2.4
Name: llama-index-llms-mistral-rs
Version: 0.4.1
Summary: llama-index llms mistral-rs integration
Author: EricLBuehler
Maintainer: jerryjliu
License-Expression: MIT
License-File: LICENSE
Requires-Python: <4.0,>=3.9
Requires-Dist: llama-index-core<0.15,>=0.13.0
